odoo/addons/l10n_it_abicab/README.rst
odoo/addons/l10n_it_abicab/__init__.py
odoo/addons/l10n_it_abicab/__manifest__.py
odoo/addons/l10n_it_abicab/i18n/de.po
odoo/addons/l10n_it_abicab/i18n/it.po
odoo/addons/l10n_it_abicab/i18n/l10n_it_abicab.pot
odoo/addons/l10n_it_abicab/i18n/nb_NO.po
odoo/addons/l10n_it_abicab/i18n/sl.po
odoo/addons/l10n_it_abicab/models/__init__.py
odoo/addons/l10n_it_abicab/models/abicab.py
odoo/addons/l10n_it_abicab/readme/CONTRIBUTORS.rst
odoo/addons/l10n_it_abicab/readme/DESCRIPTION.rst
odoo/addons/l10n_it_abicab/static/description/icon.png
odoo/addons/l10n_it_abicab/static/description/index.html
odoo/addons/l10n_it_abicab/tests/__init__.py
odoo/addons/l10n_it_abicab/tests/test_abicab.py
odoo/addons/l10n_it_abicab/views/abicab_view.xml
odoo12_addon_l10n_it_abicab-12.0.1.1.1.99.dev5.dist-info/METADATA
odoo12_addon_l10n_it_abicab-12.0.1.1.1.99.dev5.dist-info/WHEEL
odoo12_addon_l10n_it_abicab-12.0.1.1.1.99.dev5.dist-info/top_level.txt
odoo12_addon_l10n_it_abicab-12.0.1.1.1.99.dev5.dist-info/RECORD
